{
  "kind": "collectionType",
  "collectionName": "projects",
  "info": {
    "singularName": "project",
    "pluralName": "projects",
    "displayName": "Project"
  },
  "options": {
    "draftAndPublish": true
  },
  "pluginOptions": {},
  "attributes": {
    "Name": {
      "type": "string",
      "required": true
    },
    "Slug": {
      "type": "uid",
      "targetField": "Name",
      "required": true
    },
    "Year_Created": {
      "type": "string"
    },
    "Project_Type": {
      "type": "string"
    },
    "Contributors_Owners": {
      "type": "string"
    },
    "First_Project_Text": {
      "type": "text"
    },
    "First_Project_Subtext": {
      "type": "text"
    },
    "Second_Project_Text": {
      "type": "text"
    },
    "Second_Project_Subtext": {
      "type": "text"
    },
    "Project_Image": {
      "allowedTypes": [
        "images",
        "files",
        "videos",
        "audios"
      ],
      "type": "media",
      "multiple": true
    }
  }
}
